serializer_prefetch/__init__.py
serializer_prefetch/base.py
serializer_prefetch/utils.py
tests/__init__.py
tests/models.py
tests/serializers.py
tests/settings.py
tests/test_conditions.py
tests/test_errors.py
tests/test_serializers.py
drf_serializer_prefetch-1.1.12.dist-info/LICENSE
drf_serializer_prefetch-1.1.12.dist-info/METADATA
drf_serializer_prefetch-1.1.12.dist-info/WHEEL
drf_serializer_prefetch-1.1.12.dist-info/top_level.txt
drf_serializer_prefetch-1.1.12.dist-info/RECORD
