Metadata-Version: 2.1
Name: drf-serializer-prefetch
Version: 1.1.12
Summary: An automatic prefetcher for django-rest-framework.
Home-page: https://github.com/MaxDude132/drf-serializer-prefetch
Author: Maxime Toussaint
Author-email: m.toussaint@mail.com
License-File: LICENSE
Requires-Dist: django >=3.2.0
Requires-Dist: djangorestframework >=3.12
